{
  "generated_at": "2026-04-26T18:40:17",
  "tokens": {
    "dmhwYYmsI84GmTrGysK-nJuPtOlGCPmUQX9Yi5h4Zmo": {
      "holder_id": "A",
      "name": "Markus Blaurock",
      "balance_broker": 1254.83,
      "balance_giro": 1933.97,
      "capital": 5050.0,
      "allocated_pnl": -752.86,
      "allocated_expenses": 1108.33,
      "as_of": "2026-04-26",
      "currency": "EUR",
      "recent_trades": [
        {
          "date": "2026-04-21",
          "symbol": "SPXW 21APR26 7055 P",
          "pnl_eur": -289.95
        },
        {
          "date": "2026-04-21",
          "symbol": "SPXW 21APR26 7065 P",
          "pnl_eur": 289.09
        },
        {
          "date": "2026-04-20",
          "symbol": "SPXW 20APR26 7040 P",
          "pnl_eur": -104.77
        }
      ]
    },
    "Q-mrNa3YMHRJh1PrYQt-bPAJHcATYupYEchWp6qG3fc": {
      "holder_id": "B",
      "name": "CaH",
      "balance_broker": 5269.03,
      "balance_giro": 8120.74,
      "capital": 15000.0,
      "allocated_pnl": -501.91,
      "allocated_expenses": 1108.33,
      "as_of": "2026-04-26",
      "currency": "EUR",
      "recent_trades": [
        {
          "date": "2026-04-21",
          "symbol": "SPXW 21APR26 7055 P",
          "pnl_eur": -289.95
        },
        {
          "date": "2026-04-21",
          "symbol": "SPXW 21APR26 7065 P",
          "pnl_eur": 289.09
        },
        {
          "date": "2026-04-20",
          "symbol": "SPXW 20APR26 7040 P",
          "pnl_eur": -104.77
        }
      ]
    }
  }
}